setup.py
Konfikjure.egg-info/PKG-INFO
Konfikjure.egg-info/SOURCES.txt
Konfikjure.egg-info/dependency_links.txt
Konfikjure.egg-info/top_level.txt
bin/konfikjure
konfikjure/__init__.py
konfikjure/colors.py
konfikjure/config.py
konfikjure/validator.py