Metadata-Version: 1.0
Name: Konfikjure
Version: 0.1.1
Summary: Command-line based configuration utility
Home-page: UNKNOWN
Author: Jurriaan Bremer
Author-email: jurriaanbremer@gmail.com
License: GPLv3
Platform: UNKNOWN
